grexxconnect_ess/__init__.py
grexxconnect_ess/client.py
grexxconnect_ess/ess_connect.py
grexxconnect_ess/log.py
grexxconnect_ess/reverse.py
grexxconnect_ess-0.1.9.dist-info/METADATA
grexxconnect_ess-0.1.9.dist-info/WHEEL
grexxconnect_ess-0.1.9.dist-info/top_level.txt
grexxconnect_ess-0.1.9.dist-info/RECORD
