Metadata-Version: 2.1
Name: grexxconnect-ess
Version: 0.1.9
Summary: Grexx External System Service Helper
Home-page: UNKNOWN
Author: Grexx
Author-email: servicedesk@grexx.net
License: UNKNOWN
Platform: UNKNOWN
Classifier: Programming Language :: Python :: 3
Classifier: Programming Language :: Python :: 3.7
Requires-Dist: websockets
Requires-Dist: colorlog
